fastscript/__init__.py
fastscript/_nbdev.py
fastscript/core.py
fastscript/fastscript.py
fastscript/test_cli.py
fastscript-1.0.0.dist-info/LICENSE
fastscript-1.0.0.dist-info/METADATA
fastscript-1.0.0.dist-info/WHEEL
fastscript-1.0.0.dist-info/entry_points.txt
fastscript-1.0.0.dist-info/top_level.txt
fastscript-1.0.0.dist-info/RECORD
